ResPAN/__init__.py
ResPAN/respan.py
ResPAN-0.1.0.dist-info/LICENSE
ResPAN-0.1.0.dist-info/METADATA
ResPAN-0.1.0.dist-info/WHEEL
ResPAN-0.1.0.dist-info/top_level.txt
ResPAN-0.1.0.dist-info/RECORD
