Metadata-Version: 2.1
Name: ResPAN
Version: 0.1.0
Summary: A light structured residual autoencoder and mutual nearest neighbor paring guided adversarial network for scRNA-seq batch correction. 
Home-page: https://github.com/AprilYuge/ResPAN
Author: Yuge Wang, Tianyu Liu
Author-email: wangyuge22@qq.com
License: MIT License
Keywords: scRNA-seq,GAN,batch effect correction,neural network
Platform: UNKNOWN
Classifier: Programming Language :: Python :: 3
Classifier: License :: OSI Approved :: MIT License
Classifier: Operating System :: OS Independent
License-File: LICENSE
Requires-Dist: numpy
Requires-Dist: pandas
Requires-Dist: scipy
Requires-Dist: torch
Requires-Dist: sklearn
Requires-Dist: scanpy
